jgen.py
jgen-0.1.1.dist-info/LICENSE
jgen-0.1.1.dist-info/METADATA
jgen-0.1.1.dist-info/WHEEL
jgen-0.1.1.dist-info/entry_points.txt
jgen-0.1.1.dist-info/RECORD
